ftcSoundBar/__init__.py
ftSoundBarCtrl-1.2.dist-info/LICENSE
ftSoundBarCtrl-1.2.dist-info/METADATA
ftSoundBarCtrl-1.2.dist-info/WHEEL
ftSoundBarCtrl-1.2.dist-info/top_level.txt
ftSoundBarCtrl-1.2.dist-info/RECORD
