Metadata-Version: 2.1
Name: ftSoundBarCtrl
Version: 1.2
Summary: The ftcSoundBarPy Python Libary
Home-page: UNKNOWN
Author: Bloeckchengrafik
Author-email: ftpi@gmx.de
License: GNU General Public License v3.0
Platform: UNKNOWN
License-File: LICENSE
